MANIFEST.in
setup.py
woost/COPYRIGHT
woost/LICENSE
woost/__init__.py
woost/application.py
woost/authenticationscheme.py
woost/iconresolver.py
woost/languagescheme.py
woost/urlresolver.py
woost.egg-info/PKG-INFO
woost.egg-info/SOURCES.txt
woost.egg-info/dependency_links.txt
woost.egg-info/entry_points.txt
woost.egg-info/not-zip-safe
woost.egg-info/requires.txt
woost.egg-info/top_level.txt
woost/controllers/__init__.py
woost/controllers/asyncupload.py
woost/controllers/authentication.py
woost/controllers/autocomplete.py
woost/controllers/basecmscontroller.py
woost/controllers/cmscontroller.py
woost/controllers/cmsmetadatacontroller.py
woost/controllers/documentcontroller.py
woost/controllers/errordocumentcontroller.py
woost/controllers/feedcontroller.py
woost/controllers/filecontroller.py
woost/controllers/fileuploader.py
woost/controllers/firstchildredirectioncontroller.py
woost/controllers/formagreement.py
woost/controllers/imagescontroller.py
woost/controllers/installer.py
woost/controllers/language.py
woost/controllers/logincontroller.py
woost/controllers/module.py
woost/controllers/notifications.py
woost/controllers/passwordchangeconfirmationcontroller.py
woost/controllers/passwordchangecontroller.py
woost/controllers/publishablecontroller.py
woost/controllers/sentry.py
woost/controllers/stylescontroller.py
woost/controllers/uploadform.py
woost/controllers/uricontroller.py
woost/controllers/backoffice/__init__.py
woost/controllers/backoffice/backofficecontroller.py
woost/controllers/backoffice/basebackofficecontroller.py
woost/controllers/backoffice/changelogcontroller.py
woost/controllers/backoffice/contentcontroller.py
woost/controllers/backoffice/contentviews.py
woost/controllers/backoffice/deletecontroller.py
woost/controllers/backoffice/dragandropcontroller.py
woost/controllers/backoffice/dropblockcontroller.py
woost/controllers/backoffice/editblockscontroller.py
woost/controllers/backoffice/editcontroller.py
woost/controllers/backoffice/editstack.py
woost/controllers/backoffice/enabledtranslationseditnode.py
woost/controllers/backoffice/extensioneditnode.py
woost/controllers/backoffice/feedfieldscontroller.py
woost/controllers/backoffice/fileeditnode.py
