Metadata-Version: 1.1
Name: woost
Version: 2.7.1
Summary: Model driven multilanguage CMS.
Home-page: http://woost.info
Author: Marti Congost
Author-email: marti.congost@whads.com
License: UNKNOWN
Platform: UNKNOWN
Classifier: Development Status :: 3 - Alpha
Classifier: Environment :: Web Environment
Classifier: Framework :: ZODB
Classifier: Intended Audience :: Developers
Classifier: Intended Audience :: Information Technology
Classifier: License :: OSI Approved :: GNU Affero General Public License v3
Classifier: Natural Language :: Catalan
Classifier: Natural Language :: Spanish
Classifier: Programming Language :: Python :: 2
Classifier: Topic :: Internet :: WWW/HTTP :: Site Management
